{
  "project_info": {
    "project_number": "494873208116",
    "project_id": "mobile-health-app-1beb5",
    "storage_bucket": "mobile-health-app-1beb5.appspot.com"
  },
  "client": [
    {
      "client_info": {
        "mobilesdk_app_id": "1:494873208116:android:2bcc9e8d244c0a725f7161",
        "android_client_info": {
          "package_name": "com.adilegngr.mobile_health_app"
        }
      },
      "oauth_client": [],
      "api_key": [
        {
          "current_key": "AIzaSyCbfXfNsZwDtSXkNK7FRSWcUlYaFfV4AHw"
        }
      ],
      "services": {
        "appinvite_service": {
          "other_platform_oauth_client": []
        }
      }
    }
  ],
  "configuration_version": "1"
}